pydigitalstrom
tests
