Metadata-Version: 2.1
Name: pydigitalstrom
Version: 1.3.1
Summary: python api client for digitalSTROM
Home-page: https://github.com/lociii/pydigitalstrom
Author: Jens Nistler
Author-email: opensource@jensnistler.de
License: MIT
Keywords: digitalstrom,dss,ds
Platform: UNKNOWN
Classifier: Development Status :: 4 - Beta
Classifier: Environment :: Console
Classifier: License :: OSI Approved :: MIT License
Classifier: Programming Language :: Python :: 3
Classifier: Topic :: Home Automation
Requires-Python: >=3.7.6
